{
  "name": "Sean Frazier",
  "age": 33,
  "address": {
    "street": "Kazo Way",
    "city": "Fuludil",
    "state": "MS",
    "zip": "25714"
  },
  "contact": {
    "phone": "(913) 867-3490",
    "servicePhone": "800442639"
  },
  "birthday": "1964-03-20T16:31:09.597Z",
  "ip": "210.36.229.207",
  "foo": "bar",
  "profile": {
    "about": "Urwoc secvu hivpab hu eja jecakmo ufobe ujfaf vinov ke ogoran hospi. Okurofe sir kas nu gacguwu raw larat bal zuwe no zeosi gih uwuap soj cacenbi muteem wawilho. Ad duagi tov zoehvup utofup guzuldav sibo pu ev gub nare zihjurpok olad ke cizru hubu.",
    "bio": "Udsucod gupnuspe luvop vojfuzlib fepos tat ulokipuw nutowah ukezosute sosugnig jemfikipi zubzifi zohfavo. Wimonud fis pugad wukifoge fi ogi favhaumi nida docuzet oratu dobvuf mejep koduc mit ne gako. Ba iwumitif sebihjo setako le vo kakkow gideogo sodah inufuru oluobi sese nedrotow. Lefja kicuze vejoziv gahde supdo dazeef vic ju ugfid wotome tarozime bejdeluw urade. Bu pa tazeze je egvug oghawpuc gosgel atiron bicinuf awijoev fukvel oseratfop woliz kopvuw si veopisa."
  },
  "apiKey": "6e2d2e9fe921a2c7d47dd6dcc0e71ca8de47e439f7f7ab3e7842a1c0b22f7f2f",
  "currency": {
    "code": "JOD",
    "name": "Jordan Dinar"
  }
}