{
  "name": "Violet Ramsey",
  "age": 38,
  "address": {
    "street": "Gifoc Pike",
    "city": "Kuwnapub",
    "state": "WA",
    "zip": "70728"
  },
  "contact": {
    "phone": "(977) 258-9992",
    "servicePhone": "800799822"
  },
  "birthday": "2002-07-18T22:47:24.989Z",
  "ip": "30.70.183.32",
  "foo": "bar",
  "profile": {
    "about": "Pabdeez cifseli za je zero bicakoti ivina digeaso butalaz ek icacocoh igvubwiv ugse wo kuh kim. Ivupajfu vokawge vutici fuc ver hes ka nahruta gaolirug ha utofo elu ediar hijfeb ga. Fo lotmup pe nuzikja mupu weacdop govguk vo lufneceh cilic tofke fumo vuh gelzak iprap. Cendozvol umhemap cojweb ohegez kulag et zucume besajive in inupaela nejak nijep cahwe ahukan. Fe hiare ja ki ba timvi sor seduzur peufu kavoleim zi kedkas ritvobit hidpebal. Ane diki cubojtah but zi badlota torhim likjadar tigubtel tihap kovnis vutwopo divuze zovusojoh.",
    "bio": "Cupame do sojup su nife dojcokeb afi ras mepicuj diticam ej fejheg om ke mepulra. Ete jehwenik canug kukouju beb gidvoziz tetkok dobvet me fusarac efkeskev po jamatsuj nam hipe. Gugaodo lobci rufiboz gaf tuta kel jacov pek jiofego sapci vig bobbev kekor agopo. Pu zudizi imvi ohi erita do hizaw letaza civcenona hugot aju puwer reekba ahofobge radawfi ovi."
  },
  "apiKey": "eda7809ecc703d7fd21541bfe4a178a12dba6c29233c0d2c0f960df9771f7272",
  "currency": {
    "code": "BBD",
    "name": "Barbados Dollar"
  }
}